multi.v
module multi(
    input [7:0] a,
    input [7:0] b,
    input [7:0] c,
    input [7:0] d,
    input [1:0] addr,
    output reg [7:0] choice
);

always @(addr)
begin
    case(addr)
        2'b00 : choice <= a;
        2'b01 : choice <= b;
        2'b10 : choice <= c;
        2'b11 : choice <= d;
    endcase 
end

endmodule

register.v
module register(
    input ce,
    input clk,
    input [7:0] data_in,
    output reg [7:0] data_out
);

always @(posedge clk)
begin
    if(ce)
    begin
        data_out <= data_in;
    end
    
end

endmodule

rf.v
module rf(
    input [7:0] data_in,
    input clk,
    input ce0,
    input ce1,
    input ce2,
    input ce3,
    input [1:0] addr,
    output [7:0] data_out,

    input [7:0] data_switch
)

wire [7:0] register_line0;
wire [7:0] register_line1;
wire [7:0] register_line2;
wire [7:0] register_line3;

register register0(.data_in(data_in), .clk(clk), .ce(ce0), .data_out(register_line0));
register register1(.data_in(data_in), .clk(clk), .ce(ce1), .data_out(register_line1));
register register2(.data_in(data_in), .clk(clk), .ce(ce2), .data_out(register_line2));
register register3(.data_in(data_switch), .clk(clk), .ce(ce3), .data_out(register_line3));

multi multiplex(a.(register_line0), .b(register_line1), .c(register_line2), .d(register_line3), .addr(addr), .choice(data_out));

endmodule

v0.0/alu.v
`timescale 1ns/100ps

module alu
(
    input Ci,
    input [7:0] a,
    input [7:0] b,
    input [2:0] op,
    output [7:0] out,
    output CY
);


reg [8:0] sum;
reg [7:0] out1;
reg CY1;

    always @(*)
    begin
        case(op)
        3'b000 : begin
            sum <= a + b + Ci;
            out1 <= sum[7:0]; 
            CY1 <= sum[8];
        end
        3'b001 : out1 <= a - b - Ci;
        3'b010 : begin
            out1 <= a & b;
            CY1 <= 1'b0;
        end
        3'b011 : begin 
            out1 <= a | b;
            CY1 <= 1'b0;
        end
        3'b100 : begin
            out1 <= a ^ b;
            CY1 <= 1'b0;
        end
        3'b101 : begin
            out1 <= ~a;
            CY1 <= 1'b0;
        end
        3'b110 : out1 <= b;
        default : out1 <= b;
        endcase
    end

    assign out = out1;
    assign CY = CY1;

endmodule

module CY_reg
(
    input flag,
    input ce,
    input clk,
    output reg CY
);

always @(posedge clk)
begin
    if(ce)
    CY <= flag;
end

endmodule
/*
module alu_tb;

reg [7:0] a;
reg [7:0] b;
reg [2:0] op;
wire out;
wire cy;

alu alu_unit(.a(a), .b(b), .op(op), .CY(cy));

initial 
    begin
        a = 8'd10;
        b = 8'd2;
        op = 3'd0;
    #5  op = 3'd1;
    #5  op = 3'd2;
    #5  op = 3'd3;
    #5  op = 3'd4;
    #5  op = 3'd5;
    #5  op = 3'd6;
    #5  op = 3'd7;
    #5  op = 3'd0;
        a = 8'hff;
    #5  op = 3'd1;
    #5 $finish;
    end

    initial begin
	$dumpfile("alu_test.vcd");
	$dumpvars(0, alu_tb);
	$dumpon;
end

endmodule
*/

aku.v
module aku(
    input ce,
    input clk,
    input [7:0] data_in,
    output reg [7:0] data_out
);

always @(posedge clk)
begin
    if(ce)
    begin
        data_out <= data_in;
    end
    
end

endmodule

v0.0/operation_block.v
`timescale  1ns/100ps

`include "alu.v"
`include "aku.v"


module operation_block(
    input [2:0] operation_code,
    input aku_enable,
    input clk,
    input [7:0] in_b,
    output [7:0] out_result
);

wire [7:0] operation_result;
wire flag_transport;
wire flag_alu_in;

alu alu_unit(.a(out_result), .b(in_b), .op(operation_code), .CY(flag_transport), .out(operation_result), .Ci(flag_alu_in));
aku aku_unit(.ce(aku_enable), .clk(clk), .data_in(operation_result), .data_out(out_result));
CY_reg carry_reg(.flag(flag_transport), .ce(aku_enable), .clk(clk), .CY(flag_alu_in));

endmodule
/*

module operation_block_tb;
reg [2:0] op_code;
reg aku_enable;
reg clk;
reg [7:0] b_input;
wire [7:0] result;
wire cy;

operation_block op_bo1(.operation_code(op_code), .aku_enable(aku_enable), .clk(clk), .in_b(b_input), .out_result(result), .Carry_flag(cy));

initial begin
    forever begin
        #5 clk = ~clk;
    end
end

initial begin
    clk = 1'b0;
    b_input = 8'd10;
    op_code = 3'd6;
    aku_enable = 1'b1;
    #10 aku_enable = 1'b0;
    #20 $finish;
    
end

    initial begin
	$dumpfile("op_bl.vcd");
	$dumpvars(0, operation_block_tb);
	$dumpon;
end


endmodule
*/

instruction_decoder.v
module instruction_decoder 
(
    input [5:0] instruction,
    output reg [2:0] operation_code,
    output reg r0_write_enable,
    output reg r1_write_enable,
    output reg r2_write_enable,
    output reg r3_write_enable,
    output reg aku_enable,
    output reg [1:0] register_addr
);

always @(instruction)
begin
    aku_enable <= 1'b0;
    operation_code <= instruction[4:2];
    {r3_write_enable,r2_write_enable,r1_write_enable,r0_write_enable} <= 4'b0000;
    if (instruction[5:2] >= 3'd0 && instruction[5:2] <= 3'd6)
    begin
        aku_enable <= 1'b1;
        register_addr <= instruction[1:0];
    end

    if(instruction[5:2] == 3'd7)
    begin
        case(instruction[1:0])
            2'b00: r0_write_enable <= 1'b1;
            2'b01: r1_write_enable <= 1'b1;
            2'b10: r2_write_enable <= 1'b1;
            2'b11: r3_write_enable <= 1'b1;
        endcase
    end
      
    endcase 
end 

endmodule

v0.0/pm.v
module pm
(
    input [4:0] adr,
    output reg [5:0] data
);
reg [5:0] MEM [31:0];

initial begin
    $readmemb("prog_mem.bin", MEM);
end 

// begin
//     MEM[0] = 6'b111100;
//     MEM[1] = 6'b111100;    
//     MEM[2] = 6'b111100;
//     MEM[3] = 6'b111100;
//     MEM[4] = 6'b011111;
//     MEM[5] = 6'b011011;
// end

always @(adr) 
begin
    data <= MEM[adr];
    if(adr > 5'd5) 
        data <= 6'b111100;
end

endmodule

pc.v
module pc
( 
    input clk,
    input clr,
    output reg [4:0] data
)

always @(posedge clk)
    if (clr)
    begin
        data <= 0;
    end
    else
    begin
        data <= data + 1;
    end

endmodule

v0.0/cpu.v
`include "pc.v"
`include "pm.v"
`include "instruction_decoder.v"
`include "operation_block.v"
`include "rf.v"

module cpu(
    input clk,
    input [7:0] swiches,
    output [7:0] leds,
    input clr
);

    wire [4:0] actual_program_counter;
    wire [5:0] actual_instruction;

    wire [2:0] alu_operation_code;
    wire r0_en;
    wire r1_en;
    wire r2_en;
    wire r3_en;
    wire aku_en;
    wire [1:0] reg_ad;
    wire [7:0] register_file_out;

    pc program_counter(.clk(clk), .clr(clr), .data(actual_program_counter));
    pm program_memory(.adr(actual_program_counter), .data(actual_instruction));
    instruction_decoder id_block(.instruction(actual_instruction), .operation_code(alu_operation_code), .r0_write_enable(r0_en), .r1_write_enable(r1_en), .r2_write_enable(r2_en), .r3_write_enable(r3_en), . aku_enable(aku_en), .register_addr(reg_ad));
    operation_block block_operation1(.operation_code(alu_operation_code), .aku_enable(aku_en), .clk(clk), .in_b(register_file_out), .out_result(leds));
    rf register_file(.data_in(leds), .clk(clk), .ce0(r0_en), .ce1(r1_en), .ce2(r2_en), .ce3(r3_en), .addr(reg_ad), .data_out(register_file_out), .data_switch(swiches));

endmodule

v0.0/cpu_tb.v
`timescale 1ns/100ps

`include "cpu.v"

module cpu_tb();
reg [7:0] switch;
reg clk;
wire [7:0] led;
reg clr;


cpu cpu1(.clk(clk), .swiches(switch), .leds(led), .clr(clr));

initial begin
    clk = 1'b0;
    clr = 1'b0;
    switch = 8'h48;
    #10 clr = 1'b1;
    #100 $finish;
end

initial begin
    forever #5 clk = ~clk;
end 

initial begin
	$dumpfile("cpu.vcd");
	$dumpvars(0, cpu_tb);
	$dumpon;
end

endmodule

v0.0/cpu.vcd
$date
	Wed Oct 30 15:41:44 2024
$end
$version
	Icarus Verilog
$end
$timescale
	100ps
$end
$scope module cpu_tb $end
$var wire 8 ! led [7:0] $end
$var reg 1 " clk $end
$var reg 1 # clr $end
$var reg 8 $ switch [7:0] $end
$scope module cpu1 $end
$var wire 1 " clk $end
$var wire 1 # clr $end
$var wire 8 % swiches [7:0] $end
$var wire 8 & register_file_out [7:0] $end
$var wire 2 ' reg_ad [1:0] $end
$var wire 1 ( r3_en $end
$var wire 1 ) r2_en $end
$var wire 1 * r1_en $end
$var wire 1 + r0_en $end
$var wire 8 , leds [7:0] $end
$var wire 3 - alu_operation_code [2:0] $end
$var wire 1 . aku_en $end
$var wire 5 / actual_program_counter [4:0] $end
$var wire 6 0 actual_instruction [5:0] $end
$scope module block_operation1 $end
$var wire 1 " clk $end
$var wire 8 1 out_result [7:0] $end
$var wire 8 2 operation_result [7:0] $end
$var wire 3 3 operation_code [2:0] $end
$var wire 8 4 in_b [7:0] $end
$var wire 1 5 flag_transport $end
$var wire 1 6 flag_alu_in $end
$var wire 1 . aku_enable $end
$scope module aku_unit $end
$var wire 1 " clk $end
$var wire 8 7 data_in [7:0] $end
$var wire 1 . ce $end
$var reg 8 8 data_out [7:0] $end
$upscope $end
$scope module alu_unit $end
$var wire 1 5 CY $end
$var wire 8 9 a [7:0] $end
$var wire 8 : out [7:0] $end
$var wire 3 ; op [2:0] $end
$var wire 8 < b [7:0] $end
$var wire 1 6 Ci $end
$var reg 1 = CY1 $end
$var reg 8 > out1 [7:0] $end
$var reg 9 ? sum [8:0] $end
$upscope $end
$scope module carry_reg $end
$var wire 1 " clk $end
$var wire 1 5 flag $end
$var wire 1 . ce $end
$var reg 1 6 CY $end
$upscope $end
$upscope $end
$scope module id_block $end
$var wire 6 @ instruction [5:0] $end
$var reg 1 . aku_enable $end
$var reg 3 A operation_code [2:0] $end
$var reg 1 + r0_write_enable $end
$var reg 1 * r1_write_enable $end
$var reg 1 ) r2_write_enable $end
$var reg 1 ( r3_write_enable $end
$var reg 2 B register_addr [1:0] $end
$upscope $end
$scope module program_counter $end
$var wire 1 " clk $end
$var wire 1 # clr $end
$var reg 5 C data [4:0] $end
$upscope $end
$scope module program_memory $end
$var wire 5 D adr [4:0] $end
$var reg 6 E data [5:0] $end
$upscope $end
$scope module register_file $end
$var wire 2 F addr [1:0] $end
$var wire 1 + ce0 $end
$var wire 1 * ce1 $end
$var wire 1 ) ce2 $end
$var wire 1 ( ce3 $end
$var wire 1 " clk $end
$var wire 8 G data_in [7:0] $end
$var wire 8 H data_switch [7:0] $end
$var wire 8 I register_line3 [7:0] $end
$var wire 8 J register_line2 [7:0] $end
$var wire 8 K register_line1 [7:0] $end
$var wire 8 L register_line0 [7:0] $end
$var wire 8 M data_out [7:0] $end
$scope module multiplex $end
$var wire 2 N addr [1:0] $end
$var wire 8 O d [7:0] $end
$var wire 8 P c [7:0] $end
$var wire 8 Q b [7:0] $end
$var wire 8 R a [7:0] $end
$var reg 8 S choice [7:0] $end
$upscope $end
$scope module register0 $end
$var wire 1 + ce $end
$var wire 1 " clk $end
$var wire 8 T data_in [7:0] $end
$var reg 8 U data_out [7:0] $end
$upscope $end
$scope module register1 $end
$var wire 1 * ce $end
$var wire 1 " clk $end
$var wire 8 V data_in [7:0] $end
$var reg 8 W data_out [7:0] $end
$upscope $end
$scope module register2 $end
$var wire 1 ) ce $end
$var wire 1 " clk $end
$var wire 8 X data_in [7:0] $end
$var reg 8 Y data_out [7:0] $end
$upscope $end
$scope module register3 $end
$var wire 1 ( ce $end
$var wire 1 " clk $end
$var wire 8 Z data_in [7:0] $end
$var reg 8 [ data_out [7:0] $end
$upscope $end
$upscope $end
$upscope $end
$upscope $end
$enddefinitions $end
#0
$dumpvars
bx [
b1001000 Z
bx Y
bx X
bx W
bx V
bx U
bx T
bx S
bx R
bx Q
bx P
bx O
bx N
bx M
bx L
bx K
bx J
bx I
b1001000 H
bx G
bx F
bx E
bx D
bx C
bx B
bx A
bx @
bx ?
bx >
x=
bx <
bx ;
bx :
bx 9
bx 8
bx 7
x6
x5
bx 4
bx 3
bx 2
bx 1
bx 0
bx /
x.
bx -
bx ,
x+
x*
x)
x(
bx '
bx &
b1001000 %
b1001000 $
0#
0"
bx !
$end
#50
0(
0)
0*
0+
b111 -
b111 3
b111 ;
b111 A
0.
b111100 0
b111100 @
b111100 E
b0 /
b0 C
b0 D
1"
#100
0"
1#
#150
b1 /
b1 C
b1 D
1"
#200
0"
#250
b10 /
b10 C
b10 D
1"
#300
0"
#350
b11 /
b11 C
b11 D
1"
#400
0"
#450
1(
b11111 0
b11111 @
b11111 E
b100 /
b100 C
b100 D
1"
#500
0"
#550
b1001000 2
b1001000 7
b1001000 :
b1001000 >
b1001000 &
b1001000 4
b1001000 <
b1001000 M
b1001000 S
b11 '
b11 B
b11 F
b11 N
1.
0(
b110 -
b110 3
b110 ;
b110 A
b11011 0
b11011 @
b11011 E
b1001000 I
b1001000 O
b1001000 [
b101 /
b101 C
b101 D
1"
#600
0"
#650
b111 -
b111 3
b111 ;
b111 A
0.
b111100 0
b111100 @
b111100 E
b110 /
b110 C
b110 D
b1001000 !
b1001000 ,
b1001000 1
b1001000 8
b1001000 9
b1001000 G
b1001000 T
b1001000 V
b1001000 X
1"
#700
0"
#750
b111100 0
b111100 @
b111100 E
b111 /
b111 C
b111 D
1"
#800
0"
#850
b111100 0
b111100 @
b111100 E
b1000 /
b1000 C
b1000 D
1"
#900
0"
#950
b111100 0
b111100 @
b111100 E
b1001 /
b1001 C
b1001 D
1"
#1000
0"
#1050
b111100 0
b111100 @
b111100 E
b1010 /
b1010 C
b1010 D
1"
